labellibpy/__init__.py
labellibpy/labellib.py
tests/__init__.py
tests/unit.py
labellibpy-0.0.3.dist-info/METADATA
labellibpy-0.0.3.dist-info/WHEEL
labellibpy-0.0.3.dist-info/top_level.txt
labellibpy-0.0.3.dist-info/RECORD
