Metadata-Version: 2.1
Name: labellibpy
Version: 0.0.3
Summary: A small http client for retrieving messages from labelsys.
Home-page: https://github.com/gypz/labellib
Author: Mateus M. Souza
Author-email: mateus.souza@dmcard.com.br
License: UNKNOWN
Platform: UNKNOWN
Classifier: Programming Language :: Python :: 3
Classifier: License :: OSI Approved :: MIT License
Classifier: Operating System :: OS Independent
Requires-Python: >=3.6
Requires-Dist: requests
